setup.cfg
setup.py
seaborn_file/__init__.py
seaborn_file/file.py
seaborn_file.egg-info/PKG-INFO
seaborn_file.egg-info/SOURCES.txt
seaborn_file.egg-info/dependency_links.txt
seaborn_file.egg-info/top_level.txt
test/test_file.py