Metadata-Version: 1.1
Name: seaborn-file
Version: 1.1.1
Summary: Seaborn-File enables the manipulation of thedirectories of a computer within a program.
Home-page: https://github.com/SeabornGames/File
Author: Ben Christenson
Author-email: Python@BenChristenson.com
License: MIT License
Download-URL: https://github.com/SeabornGames/File/tarball/download
Keywords: os
Platform: UNKNOWN
Classifier: Intended Audience :: Developers
Classifier: Natural Language :: English
Classifier: License :: Other/Proprietary License
Classifier: Operating System :: POSIX :: Linux
Classifier: Programming Language :: Python
Classifier: Programming Language :: Python :: 2.7
Classifier: Programming Language :: Python :: 3.6
